supervisor/__init__.py
supervisor/childutils.py
supervisor/compat.py
supervisor/confecho.py
supervisor/datatypes.py
supervisor/dispatchers.py
supervisor/events.py
supervisor/http.py
supervisor/http_client.py
supervisor/loggers.py
supervisor/options.py
supervisor/pidproxy.py
supervisor/poller.py
supervisor/process.py
supervisor/rpcinterface.py
supervisor/services.py
supervisor/socket_manager.py
supervisor/states.py
supervisor/supervisorctl.py
supervisor/supervisord.py
supervisor/templating.py
supervisor/utils.py
supervisor/version.txt
supervisor/web.py
supervisor/xmlrpc.py
supervisor/medusa/__init__.py
supervisor/medusa/asynchat_25.py
supervisor/medusa/asyncore_25.py
supervisor/medusa/auth_handler.py
supervisor/medusa/counter.py
supervisor/medusa/default_handler.py
supervisor/medusa/filesys.py
supervisor/medusa/http_date.py
supervisor/medusa/http_server.py
supervisor/medusa/logger.py
supervisor/medusa/producers.py
supervisor/medusa/text_socket.py
supervisor/medusa/util.py
supervisor/medusa/xmlrpc_handler.py
supervisor/psutil/__init__.py
supervisor/psutil/subproc.py
supervisor/scripts/loop_eventgen.py
supervisor/scripts/loop_listener.py
supervisor/scripts/sample_commevent.py
supervisor/scripts/sample_eventlistener.py
supervisor/scripts/sample_exiting_eventlistener.py
supervisor/skel/sample.conf
supervisor/tests/__init__.py
supervisor/tests/base.py
supervisor/tests/test_childutils.py
supervisor/tests/test_confecho.py
supervisor/tests/test_datatypes.py
supervisor/tests/test_dispatchers.py
supervisor/tests/test_end_to_end.py
supervisor/tests/test_events.py
supervisor/tests/test_http.py
supervisor/tests/test_http_client.py
supervisor/tests/test_loggers.py
supervisor/tests/test_options.py
supervisor/tests/test_pidproxy.py
supervisor/tests/test_poller.py
supervisor/tests/test_process.py
supervisor/tests/test_rpcinterfaces.py
supervisor/tests/test_socket_manager.py
supervisor/tests/test_states.py
supervisor/tests/test_supervisorctl.py
supervisor/tests/test_supervisord.py
supervisor_win-4.7.0.dist-info/LICENSES.txt
supervisor_win-4.7.0.dist-info/METADATA
supervisor_win-4.7.0.dist-info/WHEEL
supervisor_win-4.7.0.dist-info/entry_points.txt
supervisor_win-4.7.0.dist-info/top_level.txt
supervisor_win-4.7.0.dist-info/RECORD
