Metadata-Version: 2.1
Name: supervisor-win
Version: 4.7.0
Summary: A system for controlling process state under WINDOWS
Home-page: http://supervisord.org/
Author: Alex
Author-email: alex@fabricadigital.com.br
Maintainer: Alex
Maintainer-email: alex@fabricadigital.com.br
License: BSD-derived (http://www.repoze.org/LICENSE.txt)
Project-URL: Changelog, http://supervisord.org/changelog
Project-URL: Documentation, http://supervisord.org
Project-URL: Issue Tracker, https://github.com/Supervisor/supervisor
Classifier: Development Status :: 5 - Production/Stable
Classifier: Environment :: No Input/Output (Daemon)
Classifier: Intended Audience :: System Administrators
Classifier: Natural Language :: English
Classifier: Operating System :: Microsoft :: Windows
Classifier: Topic :: System :: Boot
Classifier: Topic :: System :: Monitoring
Classifier: Topic :: System :: Systems Administration
Classifier: Programming Language :: Python
Classifier: Programming Language :: Python :: 2
Classifier: Programming Language :: Python :: 2.7
Classifier: Programming Language :: Python :: 3
Classifier: Programming Language :: Python :: 3.4
Classifier: Programming Language :: Python :: 3.5
Classifier: Programming Language :: Python :: 3.6
Classifier: Programming Language :: Python :: 3.7
Classifier: Programming Language :: Python :: 3.8
Classifier: Programming Language :: Python :: 3.9
Classifier: Programming Language :: Python :: 3.10
Classifier: Programming Language :: Python :: 3.11
License-File: LICENSES.txt
Requires-Dist: pywin32 (<=306,>228)
Requires-Dist: setuptools ; python_version < "3.8"
Provides-Extra: testing
Requires-Dist: pytest ; extra == 'testing'
Requires-Dist: pytest-cov ; extra == 'testing'
